{
  "generator-jhipster": {
    "applicationType": "monolith",
    "gitCompany": "",
    "baseName": "jhipsterSampleApplication",
    "packageName": "com.mycompany.myapp",
    "packageFolder": "com/mycompany/myapp",
    "serverPort": 8080,
    "serviceDiscoveryType": false,
    "authenticationType": "jwt",
    "uaaBaseName": "../uaa",
    "cacheProvider": "ehcache",
    "enableHibernateCache": true,
    "websocket": "spring-websocket",
    "databaseType": "sql",
    "devDatabaseType": "h2Disk",
    "prodDatabaseType": "mysql",
    "searchEngine": "elasticsearch",
    "enableSwaggerCodegen": "true",
    "messageBroker": "kafka",
    "buildTool": "maven",
    "useSass": true,
    "clientPackageManager": "npm",
    "testFrameworks": [],
    "enableTranslation": true,
    "nativeLanguage": "en",
    "languages": ["en"],
    "clientFramework": "angularX",
    "jhiPrefix": "jhi",
    "jhipsterVersion": "6.8.0",
    "jwtSecretKey": "ZDMyZTFjYzNkYWVlODFhOTE5YzdlODhiMzM1M2RjMzRhZWVjOTZlNGRjODg3Yjc3YjkzZGUxMWUwZDYyNTA0MTA4MTEwNGI2ZWRkMDRhNDU5ZWU5Zjk1MmRmMTcyMjMzMWI1YzI0NWIzODk5NDkyYWMxNmNkYTJhNmFjOWFkYTE=",
    "embeddableLaunchScript": false,
    "clientTheme": "none",
    "creationTimestamp": 1586921375762,
    "entitySuffix": "",
    "dtoSuffix": "DTO",
    "otherModules": [],
    "blueprints": []
  },
  "git-provider": "GitHub",
  "git-company": "JZ8012",
  "repository-name": "jhipster-sample-application"
}
